asalib/__init__.py
asalib/asamod.py
asalib-0.1.1.dist-info/METADATA
asalib-0.1.1.dist-info/WHEEL
asalib-0.1.1.dist-info/top_level.txt
asalib-0.1.1.dist-info/RECORD
