Metadata-Version: 2.1
Name: asalib
Version: 0.1.1
Summary: t.me/asalinks lib
Home-page: https://t.me/asalinks
Author: https://t.me/cagavo
Author-email: no@no.com
License: nothing
Platform: UNKNOWN
Classifier: Development Status :: 1 - Planning
Classifier: Intended Audience :: Religion
Classifier: License :: Freeware
Classifier: Natural Language :: Italian
Classifier: Operating System :: OS Independent
Classifier: Programming Language :: Python
